sdk_dados_abertos_camara/__init__.py
sdk_dados_abertos_camara/api.py
sdk_dados_abertos_camara/endpoints.py
sdk_dados_abertos_camara/exceptions.py
sdk_dados_abertos_camara/models.py
sdk_dados_abertos_camara/utils.py
tests/__init__.py
tests/test_models.py
sdk_dados_abertos_camara-0.0.9.dist-info/LICENSE
sdk_dados_abertos_camara-0.0.9.dist-info/METADATA
sdk_dados_abertos_camara-0.0.9.dist-info/WHEEL
sdk_dados_abertos_camara-0.0.9.dist-info/top_level.txt
sdk_dados_abertos_camara-0.0.9.dist-info/RECORD
