Metadata-Version: 2.1
Name: sdk-dados-abertos-camara
Version: 0.0.9
Summary: SDK to use Dados Abertos da Camara dos Deputados
Home-page: https://github.com/acompanhalegis/sdk-dados-abertos-camara-py
Author: AcompanhaLegis
License: UNKNOWN
Platform: UNKNOWN
Classifier: Programming Language :: Python :: 3
Classifier: License :: OSI Approved :: MIT License
Classifier: Operating System :: OS Independent
Requires-Python: >=3.6
Requires-Dist: requests (==2.25.1)
